libclang-17.0.6.data/platlib/clang/__init__.py
libclang-17.0.6.data/platlib/clang/cindex.py
libclang-17.0.6.data/platlib/clang/enumerations.py
libclang-17.0.6.data/platlib/clang/native/__init__.py
libclang-17.0.6.data/platlib/clang/native/libclang.dylib
libclang-17.0.6.dist-info/LICENSE.TXT
libclang-17.0.6.dist-info/METADATA
libclang-17.0.6.dist-info/WHEEL
libclang-17.0.6.dist-info/top_level.txt
libclang-17.0.6.dist-info/RECORD
